Workbook

Sheet Cover
B3: VLTD
B4: Chief Financial Officer — Financial Model
B6: Confidential · Pre-Launch · May 2026
B9: CONTENTS
B10: 1. Assumptions | C10: All model inputs — swap in real numbers here
B11: 2. Financial Model | C11: 36-month P&L · Monthly detail, quarterly rollup
B12: 3. Pricing Strategy | C12: Three pricing scenarios with conversion and LTV analysis
B13: 4. IP & Domain | C13: VLTD.com acquisition + trademark filing budget
B14: 5. Fundraising | C14: Investor-ready metrics, use of funds, valuation range
B16: Blue cells = inputs you can change | Black cells = formulas | Yellow = key assumptions

Sheet Assumptions
B2: VLTD — CFO Model Assumptions
B3: Update BLUE cells. All other tabs pull from here.
B5: PRODUCT & PRICING
B6: Paid tier monthly price | C6: 7.99 | E6: Primary scenario — see Pricing tab for alternatives
B7: Annual plan discount | C7: 0.15 | E7: Annual price = monthly × 12 × (1 - discount)
B8: % paid users on annual plan | C8: 0.3 | E8: Drives cash collection timing
B9: Free tier | C9: Yes | E9: Free forever — collector-first positioning
B11: USER GROWTH (ORGANIC — ZERO PAID ACQUISITION)
B12: Launch month | C12: Jun-26 | E12: Source: VLTD roadmap May 2026
B13: Y1 monthly new free user target | C13: 416 | E13: ~5,000 cumulative by month 12 (conservative organic)
B14: Y1 monthly growth acceleration | C14: 0.08 | E14: Month-over-month improvement in new signups
B15: Y2 avg monthly new free users | C15: 900 | E15: Press coverage + word-of-mouth effect
B16: Y3 avg monthly new free users | C16: 1800 | E16: Established brand, community growth
B18: CONVERSION & RETENTION
B19: Free-to-paid conversion rate | C19: 0.04 | E19: Industry benchmark: 2–8% for freemium consumer apps
B20: Paid monthly churn rate | C20: 0.035 | E20: Collector apps: 3–5% monthly. Improve with annual plans.
B21: Avg months to convert (free) | C21: 3 | E21: Lag between signup and upgrade decision
B23: MONTHLY OPERATING COSTS ($)
B24: Supabase (DB + Auth + Storage) | C24: 25 | E24: Free up to 500MB; ~$25 Pro; ~$200 at scale
B25: Vercel / hosting | C25: 20 | E25: Pro plan; scales with traffic
B26: Domain registrations | C26: 2 | E26: vltd.app + misc (~$25/year amortized)
B27: AI API costs (OpenAI/Anthropic) | C27: 50 | E27: Per scan AI calls; estimate 1,000 scans/mo at launch
B28: Developer contractor | C28: 0 | E28: 0 if solo; $2,000–$5,000/mo if hiring
B29: Marketing / content tools | C29: 0 | E29: Organic only per plan; $0 until paid channel test
B30: Legal / accounting | C30: 50 | E30: Monthly amortized (trademark, formation, etc.)
B31: Miscellaneous / buffer | C31: 50 | E31: App Store fees, tools, misc
B33: ONE-TIME / STARTUP COSTS ($)
B34: USPTO trademark filing — VLTD | C34: 350 | E34: TEAS Plus per class; 2 classes (software + retail) = $700
B35: Trademark attorney (optional) | C35: 1500 | E35: Full-service filing; reduces risk of rejection
B36: VLTD.com domain acquisition | C36: 2500 | E36: Budget assumption — negotiate from here
B37: LLC / Corp formation | C37: 500 | E37: Delaware C-Corp recommended if raising
B39: FUNDRAISING (IF APPLICABLE)
B40: Target raise (pre-seed) | C40: 250000 | E40: Enough for 18–24 months runway + dev hire
B41: Pre-money valuation target | C41: 1500000 | E41: 5–7x ARR at 12-month forward run rate
B42: Equity given at pre-seed | C42: 0.143 | E42: =$250K / $1.75M post = 14.3%

Sheet Financial Model
A1: VLTD — 36-Month Financial Model
C2: Year 1 (Jun '26–May '27) | O2: Year 2 (Jun '27–May '28) | AA2: Year 3 (Jun '28–May '29)
C3: Jun-26 | D3: Jul-26 | E3: Aug-26 | F3: Sep-26 | G3: Oct-26 | H3: Nov-26 | I3: Dec-26 | J3: Jan-27 | K3: Feb-27 | L3: Mar-27 | M3: Apr-27 | N3: May-27 | O3: Jun-27 | P3: Jul-27 | Q3: Aug-27 | R3: Sep-27 | S3: Oct-27 | T3: Nov-27 | U3: Dec-27 | V3: Jan-28 | W3: Feb-28 | X3: Mar-28 | Y3: Apr-28 | Z3: May-28 | AA3: Jun-28 | AB3: Jul-28 | AC3: Aug-28 | AD3: Sep-28 | AE3: Oct-28 | AF3: Nov-28 | AG3: Dec-28 | AH3: Jan-29 | AI3: Feb-29 | AJ3: Mar-29 | AK3: Apr-29 | AL3: May-29
A4: USERS
A5: New free signups (monthly) | C5: 200 | D5: 216 | E5: 233 | F5: 251 | G5: 272 | H5: 293 | I5: 317 | J5: 342 | K5: 370 | L5: 399 | M5: 431 | N5: 466 | O5: 900 | P5: 900 | Q5: 900 | R5: 900 | S5: 900 | T5: 900 | U5: 900 | V5: 900 | W5: 900 | X5: 900 | Y5: 900 | Z5: 900 | AA5: 1800 | AB5: 1800 | AC5: 1800 | AD5: 1800 | AE5: 1800 | AF5: 1800 | AG5: 1800 | AH5: 1800 | AI5: 1800 | AJ5: 1800 | AK5: 1800 | AL5: 1800
A6: Cumulative free users | C6: =C5 | D6: =C6+D5 | E6: =D6+E5 | F6: =E6+F5 | G6: =F6+G5 | H6: =G6+H5 | I6: =H6+I5 | J6: =I6+J5 | K6: =J6+K5 | ... AL6: =AK6+AL5
A7: New paid conversions | C7: =ROUND(C5*Assumptions!$C$25,0) | D7: =ROUND(D5*Assumptions!$C$25,0) | E7: =ROUND(E5*Assumptions!$C$25,0) | F7: =ROUND(F5*Assumptions!$C$25,0) | G7: =ROUND(G5*Assumptions!$C$25,0) | H7: =ROUND(H5*Assumptions!$C$25,0) | I7: =ROUND(I5*Assumptions!$C$25,0) | J7: =ROUND(J5*Assumptions!$C$25,0) | ... AL7: =ROUND(AL5*Assumptions!$C$25,0)
A8: Churned paid users | C8: =ROUND(C7*Assumptions!$C$26,0) | D8: =ROUND(C9*Assumptions!$C$26,0) | E8: =ROUND(D9*Assumptions!$C$26,0) | F8: =ROUND(E9*Assumptions!$C$26,0) | G8: =ROUND(F9*Assumptions!$C$26,0) | H8: =ROUND(G9*Assumptions!$C$26,0) | I8: =ROUND(H9*Assumptions!$C$26,0) | J8: =ROUND(I9*Assumptions!$C$26,0) | K8: =ROUND(J9*Assumptions!$C$26,0) | ... AL8: =ROUND(AK9*Assumptions!$C$26,0)
A9: Net paid users (EOP) | C9: =C7-C8 | D9: =C9+D7-D8 | E9: =D9+E7-E8 | F9: =E9+F7-F8 | G9: =F9+G7-G8 | H9: =G9+H7-H8 | I9: =H9+I7-I8 | J9: =I9+J7-J8 | K9: =J9+K7-K8 | ... AL9: =AK9+AL7-AL8
A11: REVENUE
A12: Monthly Recurring Revenue (MRR) | C12: =C9*Assumptions!$C$7 | D12: =D9*Assumptions!$C$7 | E12: =E9*Assumptions!$C$7 | F12: =F9*Assumptions!$C$7 | G12: =G9*Assumptions!$C$7 | H12: =H9*Assumptions!$C$7 | I12: =I9*Assumptions!$C$7 | J12: =J9*Assumptions!$C$7 | ... AL12: =AL9*Assumptions!$C$7
A13: Annual Recurring Revenue (ARR) | C13: =C12*12 | D13: =D12*12 | E13: =E12*12 | F13: =F12*12 | G13: =G12*12 | H13: =H12*12 | I13: =I12*12 | J13: =J12*12 | ... AL13: =AL12*12
A14: Blended ARPU (monthly) | C14: =IF(C9>0,C12/C9,0) | D14: =IF(D9>0,D12/D9,0) | E14: =IF(E9>0,E12/E9,0) | F14: =IF(F9>0,F12/F9,0) | G14: =IF(G9>0,G12/G9,0) | H14: =IF(H9>0,H12/H9,0) | I14: =IF(I9>0,I12/I9,0) | J14: =IF(J9>0,J12/J9,0) | ... AL14: =IF(AL9>0,AL12/AL9,0)
A16: OPERATING COSTS
A17: Supabase | C17: =Assumptions!$C$32 | D17: =Assumptions!$C$32 | E17: =Assumptions!$C$32 | F17: =Assumptions!$C$32 | G17: =Assumptions!$C$32 | H17: =Assumptions!$C$32 | I17: =Assumptions!$C$32 | J17: =Assumptions!$C$32 | ... AL17: =Assumptions!$C$32
A18: Vercel / hosting | C18: =Assumptions!$C$33 | D18: =Assumptions!$C$33 | E18: =Assumptions!$C$33 | F18: =Assumptions!$C$33 | G18: =Assumptions!$C$33 | H18: =Assumptions!$C$33 | I18: =Assumptions!$C$33 | J18: =Assumptions!$C$33 | ... AL18: =Assumptions!$C$33
A19: AI API costs | C19: =Assumptions!$C$35 | D19: =Assumptions!$C$35 | E19: =Assumptions!$C$35 | F19: =Assumptions!$C$35 | G19: =Assumptions!$C$35 | H19: =Assumptions!$C$35 | I19: =Assumptions!$C$35 | J19: =Assumptions!$C$35 | ... AL19: =Assumptions!$C$35
A20: Developer contractor | C20: =Assumptions!$C$36 | D20: =Assumptions!$C$36 | E20: =Assumptions!$C$36 | F20: =Assumptions!$C$36 | G20: =Assumptions!$C$36 | H20: =Assumptions!$C$36 | I20: =Assumptions!$C$36 | J20: =Assumptions!$C$36 | ... AL20: =Assumptions!$C$36
A21: Other monthly costs | C21: =Assumptions!$C$34+Assumptions!$C$37+Assumptions!$C$38 | D21: =Assumptions!$C$34+Assumptions!$C$37+Assumptions!$C$38 | E21: =Assumptions!$C$34+Assumptions!$C$37+Assumptions!$C$38 | F21: =Assumptions!$C$34+Assumptions!$C$37+Assumptions!$C$38 | G21: =Assumptions!$C$34+Assumptions!$C$37+Assumptions!$C$38 | H21: =Assumptions!$C$34+Assumptions!$C$37+Assumptions!$C$38 | I21: =Assumptions!$C$34+Assumptions!$C$37+Assumptions!$C$38 | J21: =Assumptions!$C$34+Assumptions!$C$37+Assumptions!$C$38 | ... AL21: =Assumptions!$C$34+Assumptions!$C$37+Assumptions!$C$38
A22: Total Monthly OpEx | C22: =C17+C18+C19+C20+C21 | D22: =D17+D18+D19+D20+D21 | E22: =E17+E18+E19+E20+E21 | F22: =F17+F18+F19+F20+F21 | G22: =G17+G18+G19+G20+G21 | H22: =H17+H18+H19+H20+H21 | I22: =I17+I18+I19+I20+I21 | J22: =J17+J18+J19+J20+J21 | ... AL22: =AL17+AL18+AL19+AL20+AL21
A24: P&L
A25: Gross Profit | C25: =C12-(C17+C18+C19) | D25: =D12-(D17+D18+D19) | E25: =E12-(E17+E18+E19) | F25: =F12-(F17+F18+F19) | G25: =G12-(G17+G18+G19) | H25: =H12-(H17+H18+H19) | I25: =I12-(I17+I18+I19) | J25: =J12-(J17+J18+J19) | ... AL25: =AL12-(AL17+AL18+AL19)
A26: Gross Margin % | C26: =IF(C12<>0,C25/C12,0) | D26: =IF(D12<>0,D25/D12,0) | E26: =IF(E12<>0,E25/E12,0) | F26: =IF(F12<>0,F25/F12,0) | G26: =IF(G12<>0,G25/G12,0) | H26: =IF(H12<>0,H25/H12,0) | I26: =IF(I12<>0,I25/I12,0) | J26: =IF(J12<>0,J25/J12,0) | ... AL26: =IF(AL12<>0,AL25/AL12,0)
A27: EBITDA | C27: =C12-C22 | D27: =D12-D22 | E27: =E12-E22 | F27: =F12-F22 | G27: =G12-G22 | H27: =H12-H22 | I27: =I12-I22 | J27: =J12-J22 | ... AL27: =AL12-AL22
A28: EBITDA Margin % | C28: =IF(C12<>0,C27/C12,0) | D28: =IF(D12<>0,D27/D12,0) | E28: =IF(E12<>0,E27/E12,0) | F28: =IF(F12<>0,F27/F12,0) | G28: =IF(G12<>0,G27/G12,0) | H28: =IF(H12<>0,H27/H12,0) | I28: =IF(I12<>0,I27/I12,0) | J28: =IF(J12<>0,J27/J12,0) | ... AL28: =IF(AL12<>0,AL27/AL12,0)
A29: Cumulative Cash Flow | C29: =C27 | D29: =C29+D27 | E29: =D29+E27 | F29: =E29+F27 | G29: =F29+G27 | H29: =G29+H27 | I29: =H29+I27 | J29: =I29+J27 | K29: =J29+K27 | ... AL29: =AK29+AL27

Sheet Pricing Strategy
B2: VLTD — Pricing Strategy & Scenario Analysis
B3: Assumes 5,000 free users by Month 12 · Competitor benchmarks included
B5: Metric | C5: Scenario A $4.99/mo | D5: Scenario B $7.99/mo | E5: Scenario C $12.99/mo | F5: Notes
B6: Monthly price | C6: 4.99 | D6: 7.99 | E6: 12.99
B7: Annual price (15% disc.) | C7: 50.89 | D7: 81.5 | E7: 132.49 | F7: =monthly×12×0.85
B9: COMPETITOR BENCHMARKS
B10: CLZ (comics/games) | C10: 4.99 | F10: Single category
B11: CollX (sports cards) | C11: 9.99 | F11: Single category
B12: Beckett Organize | C12: 9.99 | F12: Single category
B13: Shiny (TCG) | C13: 4.99 | F13: Single category
B14: CovrPrice (comics) | C14: 9.99 | F14: Single category
B16: FREE-TO-PAID PROJECTIONS (Mo. 12 — 5,000 free users)
B17: Conversion rate (4%) | C17: 200 | D17: 200 | E17: 200 | F17: =200 paid users
B18: Monthly paid user base | C18: 200 | D18: 200 | E18: 200 | F18: Same users, diff price
B19: MRR at Month 12 | C19: 998 | D19: 1598 | E19: 2598
B20: ARR at Month 12 | C20: 11976 | D20: 19176 | E20: 31176
B22: LTV / RETENTION ANALYSIS
B23: Avg paid lifetime (months) | C23: 28.6 | D23: 28.6 | E23: 28.6 | F23: =1/3.5% churn
B24: LTV (lifetime value) | C24: 142.86 | D24: 228.57 | E24: 371.43 | F24: =price × avg lifetime
B25: Est. CAC (organic only) | C25: 5 | D25: 5 | E25: 5 | F25: Content creation time amortized
B26: LTV : CAC ratio | C26: 28.6 | D26: 45.7 | E26: 74.3 | F26: Target: >3x. All scenarios excellent.
B28: BREAKEVEN (MONTHLY OPEX = $197/mo)
B29: Paid users needed to break even | C29: 40 | D29: 25 | E29: 16 | F29: =OpEx / monthly price
B30: Months to breakeven | C30: 3 | D30: 2 | E30: 2 | F30: Est. with organic growth curve

Sheet IP & Domain
B2: VLTD — IP & Domain Acquisition Budget
B3: File before press coverage · Estimate range based on negotiation outcome
B5: Item | C5: Low ($) | D5: Mid ($) | E5: High ($) | F5: When | G5: Notes
B6: TRADEMARK FILINGS — USPTO
B7: TEAS Plus filing fee (per class) | C7: 350 | D7: 350 | E7: 350 | F7: Now | G7: USPTO fee — non-negotiable
B8: Class 42: Software / SaaS | C8: 350 | D8: 350 | E8: 350 | F8: Now | G8: Primary class for VLTD app
B9: Class 35: Retail services (marketplace) | C9: 350 | D9: 350 | E9: 350 | F9: Now | G9: Optional but recommended
B10: Trademark attorney (full service) | C10: 0 | D10: 1500 | E10: 2500 | F10: Now | G10: $0 if self-filed; attorney reduces rejection risk
B11: International filings (Madrid Protocol) | C11: 0 | D11: 0 | E11: 3500 | F11: Year 2 | G11: Skip pre-launch; file when revenue justifies
B12: SUBTOTAL — Trademark | C12: 700 | D12: 2200 | E12: 6700
B14: DOMAIN ACQUISITION
B15: VLTD.com — acquisition (negotiated) | C15: 500 | D15: 2500 | E15: 8000 | F15: Now | G15: 4-letter .com — LLLL.com trades $500–$8K; check Sedo/Afternic
B16: VLTD.co — fallback domain | C16: 200 | D16: 500 | E16: 1500 | F16: Optional | G16: If .com owner won't sell
B17: VLTD.io — secondary | C17: 15 | D17: 40 | E17: 100 | F17: Optional | G17: Standard renewal rate; likely available
B18: Defensive registrations (.net/.org) | C18: 30 | D18: 60 | E18: 120 | F18: Optional | G18: ~$15/ea to block squatters
B19: SUBTOTAL — Domains | C19: 745 | D19: 3100 | E19: 9720
B21: LEGAL — ENTITY & IP PROTECTION
B22: Delaware C-Corp formation | C22: 0 | D22: 500 | E22: 1200 | F22: Pre-raise | G22: Stripe Atlas $500; attorney $1,200
B23: IP assignment agreement | C23: 0 | D23: 300 | E23: 800 | F23: At formation | G23: Assigns all IP from founders to entity
B24: Privacy policy + Terms of Service | C24: 0 | D24: 500 | E24: 2000 | F24: Now | G24: DIY free; attorney-drafted ~$500
B25: SUBTOTAL — Legal | C25: 0 | D25: 1300 | E25: 4000
B27: TOTAL IP & DOMAIN BUDGET | C27: 1445 | D27: 6600 | E27: 20420 | G27: Mid scenario is recommended — file trademark + buy .com
B29: CFO RECOMMENDATION
B30: 1. File TEAS Plus trademark NOW for 'VLTD' in Class 42 (software). $350. This protects the brand before any press hits.
B31: 2. Negotiate VLTD.com acquisition. Budget $2,500. Start at $500 offer; don't disclose company name or funding status.
B32: 3. Form a Delaware C-Corp BEFORE raising money. Stripe Atlas is the fastest path ($500 all-in).
B33: 4. Skip international filings until Year 2 revenue justifies the cost (~$3,500+).

Sheet Fundraising
B2: VLTD — Pre-Seed Fundraising Summary
B3: For investor conversations · All figures modeled — verify before sharing
B5: THE ASK
B6: Raise amount (pre-seed) | C6: 250000 | D6: SAFE or priced round
B7: Pre-money valuation | C7: 1500000 | D7: 5–7× forward ARR; comp to early consumer SaaS
B8: Post-money valuation | C8: 1750000 | D8: =$1.5M + $250K raise
B9: Equity dilution | C9: 0.143 | D9: =$250K / $1.75M
B10: Instrument | C10: SAFE | D10: Simple Agreement for Future Equity — fastest to close
B12: USE OF FUNDS ($250K)
B13: Product development (contractor) | C13: 120000 | D13: 48% of raise — 12 months @ $10K/mo — 1 senior eng
B14: Infrastructure & ops scaling | C14: 24000 | D14: 10% of raise — Supabase, Vercel, AI APIs — 12 months
B15: IP & legal | C15: 7500 | D15: 3% of raise — Trademark + entity formation + counsel
B16: Domain acquisition (VLTD.com) | C16: 5000 | D16: 2% of raise — Budget ceiling for negotiation
B17: Marketing & content (paid test) | C17: 25000 | D17: 10% of raise — Month 9–12 first paid channel test
B18: Founder runway | C18: 50000 | D18: 20% of raise — 12 months personal runway for 1 founder
B19: Reserve / buffer | C19: 18500 | D19: 7% of raise — Working capital buffer
B21: INVESTOR-READY METRICS (Month 12 Targets)
B22: Total registered users | C22: 5000 | D22: Conservative organic — zero paid acquisition
B23: Paid subscribers | C23: 200 | D23: 4% conversion of free base
B24: MRR at Month 12 | C24: 1598 | D24: 200 users × $7.99
B25: ARR run rate at Month 12 | C25: 19176 | D25: MRR × 12
B26: Monthly OpEx (lean) | C26: 197 | D26: Infra only — no developer salary
B27: Gross margin (infra costs only) | C27: 0.875 | D27: SaaS benchmark: >70% — VLTD exceeds
B28: Months to operational breakeven | C28: 2 | D28: At $7.99 price — 25 paid users covers OpEx
B29: LTV (at 3.5% monthly churn) | C29: 228 | D29: =$7.99 × 28.6 months
B30: LTV : CAC (organic) | C30: 45.7 | D30: Exceptional — organic acquisition only
B31: Runway (pre-seed $250K, no revenue) | C31: 1269 | D31: Days — ~42 months at $197/mo burn
B33: VALUATION CONTEXT
B34: Revenue multiple (forward ARR) | C34: 5–7× | D34: Early-stage consumer SaaS — below median 10×
B35: Comparable: CollX raise (2022) | C35: $6M Series A | D35: Single category (sports cards only)
B36: Comparable: Shiny raise | C36: Undisclosed seed | D36: TCG only
B37: VLTD differentiation | C37: Multi-category | D37: Only app covering TCG + Sports + Comics + Music + Games + Jewelry
B38: TAM (US collectibles market) | C38: $500B+ | D38: RIAA + CGC + eBay collectibles + PSA estimates
B40: MILESTONES THAT UNLOCK SERIES A CONVERSATION
B41: 1. 10,000 registered users (organic — zero paid acquisition)
B42: 2. $5,000 MRR ($60K ARR) — ~625 paid users at $7.99
B43: 3. Trademark granted and VLTD.com secured
B44: 4. 3 months consecutive MRR growth > 10%
B45: 5. One major press placement (TechCrunch, The Verge, or collector-specific press)
